lix/__init__.py
lix/cache/__init__.py
lix/color/__init__.py
lix/factorial/__init__.py
lix/fib/__init__.py
lix/math/__init__.py
lix/sort/__init__.py
lix/sqrt/__init__.py
lix-3.8.3.dist-info/METADATA
lix-3.8.3.dist-info/WHEEL
lix-3.8.3.dist-info/top_level.txt
lix-3.8.3.dist-info/RECORD
