Metadata-Version: 2.1
Name: lix
Version: 3.8.3
Summary: lix - Multi purpose package
Home-page: https://github.com/flowa-ai/lix
Author: flowa
Author-email: flowa.dev@gmail.com
License: MIT
Keywords: lix math random copy cache factorial fib fibonacci sqrt sort sorting color colorama
Classifier: License :: OSI Approved :: MIT License
Classifier: Development Status :: 5 - Production/Stable
Classifier: Development Status :: 4 - Beta
Classifier: Development Status :: 3 - Alpha
Classifier: Development Status :: 2 - Pre-Alpha
Classifier: Development Status :: 1 - Planning
Classifier: Intended Audience :: Developers
Classifier: Intended Audience :: Science/Research
Classifier: License :: OSI Approved :: MIT License
Classifier: Programming Language :: Python
Classifier: Topic :: Software Development :: Libraries
Classifier: Topic :: Software Development :: Libraries :: Python Modules
Classifier: Topic :: Scientific/Engineering
Classifier: Topic :: Scientific/Engineering :: Artificial Intelligence
Classifier: Topic :: Scientific/Engineering :: Mathematics
Classifier: Typing :: Typed
Requires-Python: >=3.6
Requires-Dist: numpy
